[{
    "id": 1,
    "name": "Mashrafe Mortaza",
    "Born": "October 5, 1983 (age 37 years), Narail District",
    "Height": "1.85 m",
    "ODIdebut": "23 November 2001 v Zimbabwe",
    "LastODI": "6 March 2020 v Zimbabwe",
    "Testdebut": "8 November 2001 v Zimbabwe",
    "salary":60000,
    "img":"http://t3.gstatic.com/images?q=tbn:ANd9GcTUita0Dueq42YemMDjR5N_-zqVnytWS_Yh2uFatPvHCDq2H0_9XuIT0nRxVN-T"
  }, {
    "id": 2,
    "name": "Tamim Iqbal",
    "Born": "March 20, 1989 (age 31 years), Chattogram",
    "ODIdebut":" 9 February 2007 v Zimbabwe",
    "LastODI":" 25 January 2021 v West Indies",
    "Testdebut":" 4 January 2008 v New Zealand",
    "LastTest": "3 February 2021 v West Indies",
    "salary":57000,
    "img":"http://t2.gstatic.com/images?q=tbn:ANd9GcQxNsVq2juC7g3XiQ4avaKKF3IFGd5ziD1gpARMRFU8dFfLefPU9O3NajEWdsWn"
    
  }, {
    "id": 3,
    "name": "Mushfiqur Rahim",
    "Born": "June 9, 1987 (age 33 years), Bogura",
    "Testdebut": "26 May 2005 v England",
    "LastTest":" 11 February 2021 v West Indies",
    "ODIdebut": "6 August 2006 v Zimbabwe",
    "LastODI":" 25 January 2021 v West Indies",
    "T20Idebut": "28 November 2006 v Zimbabwe",
    "salary":57000,
    "img": "http://t2.gstatic.com/images?q=tbn:ANd9GcTfcZjB4G7brLc0WCJTrGZg_zLhZmAvbKaflM7PLyprELSo7Zfgx4Ltn8Oa4S_i"
  }, {
    "id": 4,
    "name": "Mahmudullah",
    "Born":" February 4, 1986 (age 35 years), Mymensingh",
    "ODIdebut": "25 July 2007 v Sri Lanka",
    "Testdebut": "9 July 2009 v West Indies",
    "LastODI": "25 January 2021 v West Indies",
   " LastTest": "7 February 2020 v Pakistan",
    "T20Idebut": "1 September 2007 v Kenya",
    "salary":60000,
    "img":"http://t3.gstatic.com/images?q=tbn:ANd9GcQCc4R-JU_z5fPf-0LeFWNDwiF88Ru1_5YiwFM4HC4mN5T8tLNAbtOiF7Y5WggT"
    
  }, {
    "id": 5,
    "name": "Mustafizur Rahman",
    "Born":" September 6, 1995 (age 25 years), Satkhira District",
    "ODIdebut": "18 June 2015 v India",
    "Testdebut":" 21 July 2015 v South Africa",
    "T20Idebut":" 24 April 2015 v Pakistan",
   " Bowling": "Left-arm medium fast",
    "LastODI": "25 January 2021 v West Indies",
    "salary":14000,
    "img":"http://t0.gstatic.com/images?q=tbn:ANd9GcTl3uN5WsH81o0UU0iP7KS53zDvkZlX4IEsrCChcZJTunDJX_978F-u6Uf5KzJu"
  }, {
    "id": 6,
    "name": "Mehidy Hasan",
   "Born": "October 25, 1997 (age 23 years), Khulna",
    "Height": "1.7 m",
    "Testdebut": "20 October 2016 v England",
    "LastTest": "3 February 2021 v West Indies",
   "ODIdebut": "25 March 2017 v Sri Lanka",
    "T20Idebut": "6 April 2017 v Sri Lanka",
    "salary":28000,
    "img":"http://t0.gstatic.com/images?q=tbn:ANd9GcQw5ZUiF99pdSDIVStr0iERKz1hPs_8dZjmmomTd1BQn7ewBTFU0Z2_q-z1yAEK"
  }, {
    "id": 7,
    "name": "Soumya Sarkar",
    "Born":" February 25, 1993 (age 28 years), Satkhira District",
   " Height":" 1.83 m",
    "ODIdebut": "1 December 2014 v Zimbabwe",
    "LastODI": "25 January 2021 v West Indies",
    "Testdebut": "28 April 2015 v Pakistan",
    "LastTest": "5 September 2019 v Afghanistan",
    "salary":30000,
    "img":"http://t3.gstatic.com/images?q=tbn:ANd9GcSXwoAfcRAS1QX7mI7XqQfUEqZPnqcH8P_qHzglv4qpTYBVVkEpR92N91noMQlg"
    
  }, {
    "id": 8,
    "name": "Liton Das",
    "Born":" February 16, 1994 (age 27 years), Dinajpur",
   "ODIdebut":" 18 June 2015 v India",
    "LastODI": "25 January 2021 v West Indies",
    "Testdebut": "10 June 2015 v India",
   " T20Idebut": "5 July 2015 v South Africa",
    "LastTest": "11 February 2021 v West Indies",
    "salary":28000,
    "img":"http://t0.gstatic.com/images?q=tbn:ANd9GcTrZgyRu66_hjDCqrLVlJyQE2GmlWVZ19NygJIlT44e9F7w2ps_qzb5Kc3oYjpU"
  }, {
    "id": 9,
    "name": "Taskin Ahmed",
    "Born": "April 3, 1995 (age 25 years), Dhaka",
    "Height": "1.88 m",
    "Bowling":" Right arm fast",
    "ODIdebut": "17 June 2014 v India",
    "Testdebut": "12 January 2017 v New Zealand",
    "salary":43000,
    "img":"http://t0.gstatic.com/images?q=tbn:ANd9GcQ6FmuKI6rW3qAbf2TFKeyM2-RSJR8t7grMj9hpLWmmow_Fh1GJGu6jFNT1BZZ6"
    
  },{
    "id": 10,
    "name": "Shakib Al Hasan",
    "Born": "March 24, 1987 (age 33 years), Magura District",
    "Testdebut": "18 May 2007 v India",
    "LastTest": "5 September 2019 v Afghanistan",
    "ODIdebut": "6 August 2006 v Zimbabwe",
    "LastODI": "25 January 2021 v West Indies",
    "T20Idebut": "28 November 2006 v Zimbabwe",
    "salary":57000,
    "img":"http://t3.gstatic.com/images?q=tbn:ANd9GcSnn27coD_1wIFzntVYPE0JLeC3nuRD0TBfat56lur6gQbHFdUo0iqfQUj6sUHv"
  }]